pygeonlp/capi.cpython-39-darwin.so
pygeonlp/api/__init__.py
pygeonlp/api/__main__.py
pygeonlp/api/devtool.py
pygeonlp/api/dict_manager.py
pygeonlp/api/dictionary.py
pygeonlp/api/filter.py
pygeonlp/api/linker.py
pygeonlp/api/metadata.py
pygeonlp/api/node.py
pygeonlp/api/parser.py
pygeonlp/api/scoring.py
pygeonlp/api/service.py
pygeonlp/api/spatial_filter.py
pygeonlp/api/temporal_filter.py
pygeonlp/api/workflow.py
pygeonlp/tests/__init__.py
pygeonlp/tests/test_api.py
pygeonlp/tests/test_api_geocoder.py
pygeonlp/tests/test_api_geocoder_neologd.py
pygeonlp/tests/test_doctest.py
pygeonlp/tests/test_issue1.py
pygeonlp/tests/test_multiprocess.py
pygeonlp-1.2.2rc1.data/data/pygeonlp_basedata/edo-kiriezu-owariya.csv
pygeonlp-1.2.2rc1.data/data/pygeonlp_basedata/edo-kiriezu-owariya.json
pygeonlp-1.2.2rc1.data/data/pygeonlp_basedata/geoshape-city.csv
pygeonlp-1.2.2rc1.data/data/pygeonlp_basedata/geoshape-city.json
pygeonlp-1.2.2rc1.data/data/pygeonlp_basedata/geoshape-pref.csv
pygeonlp-1.2.2rc1.data/data/pygeonlp_basedata/geoshape-pref.json
pygeonlp-1.2.2rc1.data/data/pygeonlp_basedata/ksj-station-N02-2020.csv
pygeonlp-1.2.2rc1.data/data/pygeonlp_basedata/ksj-station-N02.csv
pygeonlp-1.2.2rc1.data/data/pygeonlp_basedata/ksj-station-N02.json
pygeonlp-1.2.2rc1.dist-info/LICENSE
pygeonlp-1.2.2rc1.dist-info/METADATA
pygeonlp-1.2.2rc1.dist-info/WHEEL
pygeonlp-1.2.2rc1.dist-info/entry_points.txt
pygeonlp-1.2.2rc1.dist-info/top_level.txt
pygeonlp-1.2.2rc1.dist-info/RECORD
