Metadata-Version: 2.1
Name: pygeonlp
Version: 1.2.2rc1
Summary: A Python module for geotagging Japanese texts.
Home-page: https://github.com/geonlp-platform/pygeonlp
Author: GeoNLP Project Team
Author-email: geonlp@nii.ac.jp
License: 2-Clause "Simplified" BSD License
Requires-Python: >=3.6.8
License-File: LICENSE
Requires-Dist: requests (>=2.31.0)
Requires-Dist: chardet (>=5.2.0)
Requires-Dist: docopt
Requires-Dist: lxml (>=4.9.1)
Requires-Dist: python-dateutil (>=2.8.1)
Requires-Dist: deprecated
Requires-Dist: jageocoder (>=2.1.0)
Requires-Dist: geographiclib (>=2.0)
